{"info":{"name":"NASA Marathon 2017","service":"youtube"},"playlist":[{"name":"NASA 2017 - Super Mario RPG: Legend of the Seven Stars (Any%) by pidgezero_one","duration":10960,"qualities":[{"src":"fdY-2px0fmE"}]},{"name":"NASA 2017 - Super Metroid (Any%) by cfb","duration":3081,"qualities":[{"src":"fLzhsVHJ3ik"}]},{"name":"NASA 2017 - Curious George (Any% Race) by TwoWorldsCoexisting & FingerQuick","duration":3781,"qualities":[{"src":"-gdtkuymeOw"}]},{"name":"NASA 2017 - Mighty Gunvolt (Gunvolt Any%) by Mr. MKL","duration":691,"qualities":[{"src":"cITWJl6PbSg"}]},{"name":"NASA 2017 - Sonic Advance (Sonic Any%) by Combo","duration":1191,"qualities":[{"src":"_tBloTg0VlA"}]},{"name":"NASA 2017 - Sonic Advance 2 (Sonic Any%) by Combo","duration":1651,"qualities":[{"src":"hgRq6Bl8AbM"}]},{"name":"NASA 2017 - Pokemon Puzzle Challenge (Intense Race) by FFRPro21 & Unusualcook","duration":1721,"qualities":[{"src":"XALzfM6LydM"}]},{"name":"NASA 2017 - Magical Tetris Challenge (Magical Tetris Expert Race) by Dark-Aries & FFRPro21","duration":1391,"qualities":[{"src":"Ez88_VUmQrI"}]},{"name":"NASA 2017 - Pokemon Puzzle League (Marathon HARD 200,000) by blinzer","duration":1041,"qualities":[{"src":"7S-UvOXfDDw"}]},{"name":"NASA 2017 - BattleTanx: Global Assault (Any%) by jymotion","duration":1781,"qualities":[{"src":"oJaHe_mDL3I"}]},{"name":"NASA 2017 - Donkey Kong Country 2: Diddy's Kong Quest (Any%) by cfb","duration":3211,"qualities":[{"src":"5MLM9fpzhrA"}]},{"name":"NASA 2017 - Donkey Kong Country 3: Dixie Kong's Double Trouble! (103%) by RaikouRider","duration":7781,"qualities":[{"src":"jKqXlTDRJEg"}]},{"name":"NASA 2017 - The Legend of Zelda (Second Quest ACE) by gamestabled","duration":511,"qualities":[{"src":"b1NuVLqF1Qc"}]},{"name":"NASA 2017 - Super Mario 3D Land (Any% Warpless) by gamestabled","duration":4121,"qualities":[{"src":"lt2CY7c7C5Y"}]},{"name":"NASA 2017 - Pokemon Green (Any%) by quo","duration":491,"qualities":[{"src":"71ZSamtoQpg"}]},{"name":"NASA 2017 - NieR (NG+) by MASH","duration":5761,"qualities":[{"src":"FbWyQpB2DRc"}]},{"name":"NASA 2017 - NieR: Automata (Any% NG) by Trineas","duration":7061,"qualities":[{"src":"62iCep5QvkE"}]},{"name":"NASA 2017 - Grabbed by the Ghoulies (NG+) by TwoWorldsCoexisting","duration":7781,"qualities":[{"src":"ESgM8zRdDLQ"}]},{"name":"NASA 2017 - Gothic (Any%) by colin8seven","duration":1411,"qualities":[{"src":"xJIuGCc50yw"}]},{"name":"NASA 2017 - Duty Calls (Any%) by colin8seven","duration":291,"qualities":[{"src":"Qw61D9KbfBM"}]},{"name":"NASA 2017 - Ninja Pizza Girl (All Deliveries) by ThoseCrazyGuys","duration":2481,"qualities":[{"src":"mOKirSpStQg"}]},{"name":"NASA 2017 - Legend of Zelda: Link's Awakening (100% Reverse Boss Order 3-Hearts Only) by MyOhMyke","duration":4121,"qualities":[{"src":"B4fMeiVaNzw"}]},{"name":"NASA 2017 - Lego Racers (Any%) by Yvathacal","duration":2771,"qualities":[{"src":"mSp66XRpfeA"}]},{"name":"NASA 2017 - Pokemon Red/Blue (Any% Glitchless) by Elminster","duration":7281,"qualities":[{"src":"Q5W76Jote44"}]},{"name":"NASA 2017 - Resident Evil 7 (NG+ Any%) by Mechapope1","duration":5751,"qualities":[{"src":"6V50_E3GptA"}]},{"name":"NASA 2017 - The Room Tribute (Any%) by Mechapope1","duration":1071,"qualities":[{"src":"riXrGOYzWcQ"}]},{"name":"NASA 2017 - Whirl Tour (100%) by Tridenttail","duration":3471,"qualities":[{"src":"Tv4PDqDySbQ"}]},{"name":"NASA 2017 - The Legend of Zelda - Randomizer (Maelstrom Flags Race) by JanusZeal & RaikouRider","duration":5681,"qualities":[{"src":"Gbh0uqrub0Q"}]},{"name":"NASA 2017 - Super Mario Bros (Any% Warps) by gamestabled","duration":1081,"qualities":[{"src":"Ofeu8qcilAc"}]},{"name":"NASA 2017 - Sonic Adventure DX (Sonic's Story) by Therio","duration":2413,"qualities":[{"src":"N_oX5ZoYkcU"}]},{"name":"NASA 2017 - Sonic Adventure 2 Battle (Hero Story) by Darkpr0","duration":2569,"qualities":[{"src":"E7vJh07plI0"}]},{"name":"NASA 2017 - Burnout 2: Point of Impact (Championship) by geurge","duration":4531,"qualities":[{"src":"RenDGotr0L4"}]},{"name":"NASA 2017 - Sunset Overdrive (Any% Classic) by Thosecrazyguys","duration":14601,"qualities":[{"src":"RVhqWw1E4cg"}]},{"name":"NASA 2017 - Stick It to the Man! (Any%) by emeraldaly","duration":1821,"qualities":[{"src":"eYeTfQlt_tA"}]},{"name":"NASA 2017 - The Legend of Zelda: The Minish Cap (Any%) by quo","duration":7281,"qualities":[{"src":"nVhT8a1Vpzs"}]},{"name":"NASA 2017 - Quest RPG: Brian's Journey (Any%) by Bingchang","duration":8061,"qualities":[{"src":"SmXsJ_w1AxM"}]},{"name":"NASA 2017 - Marvel Land (Digest) by Therio","duration":401,"qualities":[{"src":"X5E-IShdPu8"}]},{"name":"NASA 2017 - System Shock: Enhanced Edition (Any% Default Difficulty) by PvtCb","duration":921,"qualities":[{"src":"HSFLGZ1inJk"}]},{"name":"NASA 2017 - F-Zero GX (All Tracks) by AKC12","duration":4381,"qualities":[{"src":"nyCy1qIHlxk"}]},{"name":"NASA 2017 - Garfield: Caught in the Act (Any%) by Glitchymon","duration":1391,"qualities":[{"src":"2bJvGJ4hUCA"}]},{"name":"NASA 2017 - Vampire: The Masquerade - Bloodlines (Any% Nosferatu) by lurk","duration":3581,"qualities":[{"src":"EndRvrEW_0k"}]},{"name":"NASA 2017 - Tetris Grand Master Block by Colour_Thief & DeHackED","duration":1841,"qualities":[{"src":"Q7dSj1RvHVA"}]},{"name":"NASA 2017 - Catherine (Tower of Babel Co-op) by Colour_Thief & DeHackED","duration":2401,"qualities":[{"src":"uTC2L9yyDi4"}]},{"name":"NASA 2017 - Chameleon Twist (Any% Race) by Bingchang & SluckySeven","duration":1181,"qualities":[{"src":"iAouhve-6Qs"}]},{"name":"NASA 2017 - The Legend of Zelda: Ocarina of Time (Medallions, Stones, Trials) by glitchymon","duration":8921,"qualities":[{"src":"aD1NWAmICZY"}]},{"name":"NASA 2017 - Diddy Kong Racing (Any%) by Prakcity","duration":3181,"qualities":[{"src":"HkNn-CviXI4"}]},{"name":"NASA 2017 - Pokemon Snap (100%) by quo","duration":1621,"qualities":[{"src":"iDHDNuRcBjU"}]},{"name":"NASA 2017 - Dishonored 2 (Any%) by DrTChops","duration":2331,"qualities":[{"src":"ms3O57jl4-U"}]},{"name":"NASA 2017 - Onechanbara Z2: Chaos (Story Mode Any% Casual) by MASH","duration":4721,"qualities":[{"src":"QHE057QDIVI"}]},{"name":"NASA 2017 - Murdered: Soul Suspect (Any%) by Emeraldaly","duration":4486,"qualities":[{"src":"ZDhAKWJROuY"}]},{"name":"NASA 2017 - skate. (Career) by tridenttail","duration":5431,"qualities":[{"src":"6VIKu4P32A8"}]},{"name":"NASA 2017 - Super Mario 3D World (Any%) by peteyboo","duration":6601,"qualities":[{"src":"HVOKC5HMDsk"}]},{"name":"NASA 2017 - No More Heroes (Any%) by PvtCb","duration":11801,"qualities":[{"src":"EetgM1pMlOM"}]},{"name":"NASA 2017 - Zombies Ate My Neighbours (Any%) by lurk","duration":2421,"qualities":[{"src":"q5wILp477fE"}]},{"name":"NASA 2017 - Wario's Woods (Any% Race) by cyghfer & peteyboo","duration":2931,"qualities":[{"src":"bt9iLfnw97E"}]},{"name":"NASA 2017 - Dark Souls (All Bosses Race) by Mechapope1, NaxHPL, & Zazztrain","duration":7671,"qualities":[{"src":"cCThcR9x_E4"}]},{"name":"NASA 2017 - Diablo 3 (Any% NG+ Wizard) by Gandair","duration":4581,"qualities":[{"src":"E1SFrEzTBJk"}]},{"name":"NASA 2017 - Fable: The Lost Chapters (Any%) by Biglaw","duration":6741,"qualities":[{"src":"uMMoemewVio"}]},{"name":"NASA 2017 - Land Before Time: Return to the Great Valley (Any%) by zazztrain","duration":1291,"qualities":[{"src":"Uju6hmxR58g"}]},{"name":"NASA 2017 - The Elder Scrolls III: Morrowind (All Main Quests) by DrTChops","duration":1911,"qualities":[{"src":"jPwAuyRMG38"}]},{"name":"NASA 2017 - Rot Gut (Any%) by DrTChops","duration":351,"qualities":[{"src":"B_p7R8F1cQw"}]},{"name":"NASA 2017 - Star Wars: Episode 1 Racer (Any%) by Tolarus","duration":2421,"qualities":[{"src":"Stw480Qjgpo"}]},{"name":"NASA 2017 - Mario Golf (Any%) by Naegleria","duration":4091,"qualities":[{"src":"oCXg5qCzIFk"}]},{"name":"NASA 2017 - Mario Golf: Advance Tour (Story Mode Singles) by FFRPro21","duration":3611,"qualities":[{"src":"3hCocXAqrmQ"}]},{"name":"NASA 2017 - Goof Troop (Any% Co-op) by cyghfer & jymotion","duration":1331,"qualities":[{"src":"tkQqMdmN7lA"}]},{"name":"NASA 2017 - Thomas Was Alone (Any% Comfy) by jymotion","duration":3421,"qualities":[{"src":"fngRTlRYY6c"}]},{"name":"NASA 2017 - Bomberman 64 (120 Cards) by SluckySeven","duration":7021,"qualities":[{"src":"PA2rRAGeH58"}]},{"name":"NASA 2017 - Grand Theft Auto: The Ballad of Gay Tony (Any% Co-op) by Lanayru & PossessedWarrior","duration":7621,"qualities":[{"src":"zieYrYI1tyE"}]},{"name":"NASA 2017 - Crusader of Centy (All Bosses) by geurge","duration":3371,"qualities":[{"src":"EkHd-bxoPI8"}]},{"name":"NASA 2017 - Normy's Beach Babe-o-Rama (Any% Co-op) by BroBuzz & Unusualcook","duration":1821,"qualities":[{"src":"_b-br3KVobM"}]},{"name":"NASA 2017 - Max Payne 2: The Fall of Max Payne (Any%) by Shrimp","duration":2401,"qualities":[{"src":"Xie9YeJXXgY"}]},{"name":"NASA 2017 - Harvester (Any%) by Tolarus","duration":1251,"qualities":[{"src":"-apr1N89ogk"}]},{"name":"NASA 2017 - Octodad: Dadliest Catch (Any%) by fog","duration":1141,"qualities":[{"src":"DuiTu3vQJKQ"}]},{"name":"NASA 2017 - Jet Set Radio Future (Any% Coop Race) by xjabro & Xano, Fingerquick &TwoWorldsCoexisting","duration":7501,"qualities":[{"src":"aydV0ywwkD8"}]},{"name":"NASA 2017 - Tony Hawk's Project 8 (All Secret Spots) by fog","duration":1141,"qualities":[{"src":"3IbBZCNcsEc"}]},{"name":"NASA 2017 - Hydro Thunder Hurricane (All Races w/ DLC Tempest) by FingerQuick","duration":1591,"qualities":[{"src":"gGGL8M0cz0A"}]},{"name":"NASA 2017 - Typing of the Dead (Arcade Mode) by MyOhMyke","duration":2001,"qualities":[{"src":"fmXlhl3g_vw"}]},{"name":"NASA 2017 - Earthbound (Pajama%) by MyOhMyke","duration":8651,"qualities":[{"src":"JDQ--vEDM60"}]},{"name":"NASA 2017 - VVVVVV (Any% No Telejump) by IceFlinger","duration":1001,"qualities":[{"src":"r5VqbUYCphk"}]},{"name":"NASA 2017 - Tony Hawk's Underground (Any% Beginner) by Biglaw","duration":2261,"qualities":[{"src":"B-kqKkcO0B0"}]},{"name":"NASA 2017 - PewDiePie: Legend of Brofist (Any%) by ryedawg","duration":2521,"qualities":[{"src":"VRfpEpt63Y8"}]},{"name":"NASA 2017 - Trespasser: Jurassic Park (Any% Race) by lurk & SlayerofBabies + FINALE","duration":4131,"qualities":[{"src":"mFTnmKcRku4"}]},{"name":"NASA 2017 BONUS STREAM - Legend of Zelda - Randomizer (Showcase Flags%) by RaikouRider & JanusZeal","duration":1571,"qualities":[{"src":"T5NN-NKReL4"}]},{"name":"NASA 2017 BONUS STREAM - MacBat 64 (Any%) by Bingchang","duration":981,"qualities":[{"src":"UsZ9VoxdfhQ"}]},{"name":"NASA 2017 BONUS STREAM - Daffy Duck: The Marvin Missions (Any%) by lurk","duration":1221,"qualities":[{"src":"A-Won3t8CZQ"}]},{"name":"NASA 2017 BONUS STREAM - Ninja Gaiden 2 (Any%) by cfb","duration":1071,"qualities":[{"src":"mPH7bKdmCQc"}]},{"name":"NASA 2017 BONUS STREAM - Contradiction: Spot the Liar! (Any%) by lurk + BONUS FINALE!","duration":7973,"qualities":[{"src":"AccV94rSJHk"}]},{"name":"NASA 2017 BONUS STREAM - Typing of the Dead II (Any% Romaji Mode) by MyOhMyke","duration":2401,"qualities":[{"src":"3Bv2R7TcBa8"}]},{"name":"NASA 2017 BONUS STREAM - Hamtaro: Ham-Hams Unite (Any%) by MyOhMyke","duration":3131,"qualities":[{"src":"XrD_PDaB2ko"}]},{"name":"NASA 2017 BONUS STREAM - Doshin the Giant (Any%) by PvtCb","duration":4431,"qualities":[{"src":"HNjQLfUOPos"}]},{"name":"NASA 2017 BONUS STREAM - Chantelise (Any%) by Enasper","duration":3435,"qualities":[{"src":"3AjgIzkNMAI"}]},{"name":"NASA 2017 BONUS STREAM - Metal Slug 3 (Medium) by Enasper","duration":2111,"qualities":[{"src":"u7FkMUWKQvY"}]},{"name":"NASA 2017 BONUS STREAM - Resident Evil Revelations 2 (Raid Mode Medal%) by MASH","duration":5301,"qualities":[{"src":"Wswa2K0tjx0"}]},{"name":"NASA 2017 BONUS STREAM - Castlevania: Harmony of Despair (Solo, Chapters 1-6, Hard, NG+) by MASH","duration":1301,"qualities":[{"src":"_FOxbNRK6ZY"}]},{"name":"NASA 2017 BONUS STREAM - Altered Beast (Beat the Game Co-op) by MASH & Dark-Aries","duration":1591,"qualities":[{"src":"TvrUEcSEOjE"}]},{"name":"NASA 2017 BONUS STREAM - Quest 64 (US Any%) by Bingchang","duration":7551,"qualities":[{"src":"rxaf4o38fLY"}]}]}