{"info":{"name":"European Speedrunner Assembly 2016","player":"youtube","note":"Missing Freedom Planet by SuccintPunchy"},"playlist":[{"name":"#ESA16 - Dark Souls 3 [All Bosses] by Elajjaz","duration":5337,"src":"gsbIG1N1Cns"},{"name":"#ESA16 - Hitman 2: Silent Assassin [PRO/SA] by Kotti","duration":4299,"src":"XciNgNlQmPs"},{"name":"#ESA16 - Bloodborne [All Bosses with DLC] by MrTakahashi","duration":5912,"src":"zp-hxgQTlBs"},{"name":"#ESA16 - Prince of Persia: The Two Thrones [Any%] by criban","duration":4042,"src":"mLEWAzHcFNo"},{"name":"#ESA16 - Tekken 3 [Unlock All Endings (1 Round)] by Shirdel","duration":4345,"src":"aYq9MehyX_M"},{"name":"#ESA16 - Final Fantasy XII [Any%] by Freddeh","duration":25062,"src":"-3Fr0SH0V8o"},{"name":"#ESA16 - Harry Potter and the Philosopher's Stone (PC) [Any%] by Respirte","duration":5639,"src":"HjFnn5L-DSs"},{"name":"#ESA16 - Croc: Legend of the Gobbos [100%] by Puppetmaster","duration":6368,"src":"V18eOMY4ehM"},{"name":"#ESA16 - Yu-Gi-Oh! Forbidden Memories [Any% New Game+] by Mergy","duration":2907,"src":"MoS8NgkTJHw"},{"name":"#ESA16 - Futurama [Any%] by Henneko_","duration":4683,"src":"MhRoAvIzoWo"},{"name":"#ESA16 - Fallout 4 [Any%] by BubblesDelFuego","duration":4074,"src":"zcMSyKqKqaY"},{"name":"#ESA16 - Borderlands 2 [4-Player Co-Op] by Incalex, Vemirtar, Filly_Vinyl and Stenkaempen","duration":7143,"src":"Oq_vkWVnhrc"},{"name":"#ESA16 - Grand Theft Auto: The Lost and Damned (Any%) by Noz","duration":5142,"src":"IQ5xBrhBUuM"},{"name":"#ESA16 - Tomb Raider: The Last Revelation [Any%] by xRikux89","duration":5929,"src":"0qKM_8V-6KE"},{"name":"#ESA16 - Two Worlds [All Main Quests] by Shaddex","duration":3934,"src":"m1rvot7PBU8"},{"name":"#ESA16 - Fable: The Lost Chapters [Any%] by Etem_T","duration":5757,"src":"wEIFJsAjB-Y"},{"name":"#ESA16 - The Elder Scrolls III: Morrowind [All Main Quests] by DrTChops","duration":1695,"src":"zE1961IlFws"},{"name":"#ESA16 - Dishonored [Non-Lethal/Ghost] by JanMumrik","duration":2628,"src":"aIrV_Et0AEY"},{"name":"#ESA16 - Tomb Raider II (Any%) by xRikux89","duration":4897,"src":"Jq5Z2E7vOKA"},{"name":"#ESA16 - Goat Simulator [All Trophies] by Riekelt","duration":1878,"src":"6KhNqmJcH0c"},{"name":"#ESA16 - Ratchet & Clank [NG+] by Ricky","duration":1640,"src":"DTJLO7wdfs4"},{"name":"#ESA16 - Uncharted 2: Among Thieves [Any%] by epicdudeguy","duration":6605,"src":"jOAjw54TmbE"},{"name":"#ESA16 - Just Cause (Any%) by Nord","duration":6739,"src":"Q47RcgI-M6k"},{"name":"#ESA16 - Herc's Adventures [any%] by chfou","duration":4219,"src":"CVz1NPvreuw"},{"name":"#ESA16 - Half-Life [Any%] by COOLKID","duration":2672,"src":"sFk8HiN8J30"},{"name":"#ESA16 - Disgaea 2: Dark Hero Days [Any%] by PinkPajamas","duration":8453,"src":"AfdP5lGdc6I"},{"name":"#ESA16 - Metroid Fusion [100%] by Eagle","duration":6594,"src":"75MpzVpQ1PY"},{"name":"#ESA16 - Spyro 2: Riptos Rage! [100%] by Tyzerra","duration":6673,"src":"Gua6o5Iqd_o"},{"name":"#ESA16 - Super Mario 64 [120 Star Relay] by flippy_o, dwhatever, fuzzyness, noizeeh, mashsrl, srb  a","duration":10403,"src":"4to9gvRsp2A"},{"name":"#ESA16 - PoP: The Sands of Time [Any% Zipless (Race)] by tocaloni1 and epicdudeguy","duration":5136,"src":"SXK498EudVo"},{"name":"#ESA16 - Super Mario Bros. 3 [100%] by Kirua","duration":4415,"src":"m1ubychg2iM"},{"name":"#ESA16 - Arabian Nights [Any%] by Kotti","duration":2644,"src":"RZHVbBscbx8"},{"name":"#ESA16 - Outlast (No OoB) by Tirean","duration":2586,"src":"HeBLnp8U-uI"},{"name":"#ESA16 - Driver: You Are The Wheelman [Any% PS (Race)] by pitpo, Mhmd_FVC, Nozlar and ultimaomega07","duration":6329,"src":"LbZ_MTqw8uw"},{"name":"#ESA16 - Wario Land 3 [Any%] by pr0te","duration":3051,"src":"-uEfnGlVWPw"},{"name":"#ESA16 - American McGee's Alice (Any%) by Arctice","duration":3749,"src":"HycwsdTsV_8"},{"name":"#ESA16 - TimeSplitters 2 [Any% easy] by JangBang","duration":2201,"src":"4X3vvtfCmIE"},{"name":"#ESA16 - Grand Theft Auto III [Any%] by karl__k","duration":4299,"src":"weRNA7Z_TbE"},{"name":"#ESA16 - Catherine [Any% Normal] by Mrzwanzig","duration":6402,"src":"FQhxpxJf81A"},{"name":"#ESA16 - Command & Conquer: Generals  [China campaign] by tyriounet","duration":2791,"src":"Ov1-9BIBdlc"},{"name":"#ESA16 - You Are Empty [Any% with sprint] by Tezur0","duration":2613,"src":"HxDCs4WZSlU"},{"name":"#ESA16 - The Binding of Isaac: Afterbirth [Hard The Lost] by Shigan","duration":1842,"src":"f-3ITcLLABw"},{"name":"#ESA16 - Serious Sam HD: The First Encounter [Any% - Tourist] by Tezur0","duration":2676,"src":"4hK7lpLd5Ss"},{"name":"#ESA16 - Lands of Lore III [Any%] by cruxit","duration":3008,"src":"uiF58W56jE8"},{"name":"#ESA16 - Star Trek: Voyager - Elite Force [Any%] by Sphere","duration":3252,"src":"-to7i0xgc04"},{"name":"#ESA16 - Resident Evil 3: Nemesis (Any%) by Magn00zl","duration":2700,"src":"pEk040xHV14"},{"name":"#ESA16 - Resident Evil 0 Remaster [Wesker Mode] by Pessimism","duration":4703,"src":"W_1NNgG8oEs"},{"name":"#ESA16 - Total Overdose [Any%] by zoton2","duration":3870,"src":"lvzTJY9TH08"},{"name":"#ESA16 - BioShock Infinite [Any%] by heny","duration":6979,"src":"p6ecRUHiEjY"},{"name":"#ESA16 - Thief: Gold [Any% normal] by pitpo","duration":3483,"src":"k-8esXznsko"},{"name":"#ESA16 - The Elder Scrolls V: Skyrim [Any%] by 5exual_Tyrannosaurus","duration":2807,"src":"-3tqOdCnEsU"},{"name":"#ESA16 - Pokémon Snap [100%] by Drogeriehund","duration":1674,"src":"Iy4GO_av9PY"},{"name":"#ESA16 - I Wanna Be The Boshy [Any% (Dark Boshy, No Wrong Warp)] by BBF","duration":2372,"src":"VYsctlNstdc"},{"name":"#ESA16 - Super Mario World [96 Exits] by Akisto","duration":5248,"src":"-V7gMiuHMc8"},{"name":"#ESA16 - Star Wars Jedi Knight: Jedi Academy (Any%) by Sajiki","duration":2158,"src":"A4oLbcjYqcI"},{"name":"#ESA16 - Nintendo Nightmare [Any%] by Pull","duration":1743,"src":"G-_e9rwEr24"},{"name":"#ESA16 - Jak II [Any% (Race)] by Raccoon_1337, I300M3R, ThaRixer and Dexz","duration":4292,"src":"GO-nonv9TOM"},{"name":"#ESA16 - Tetris The Grand Master 3: Terror Instinct [Exhibition block] by Qlex","duration":1140,"src":"P5MkSJIkxD0"},{"name":"#ESA16 - The Legend of Zelda: A Link to the Past [No Major Glitches] by KRob16","duration":5996,"src":"MNgWUKTTdzs"},{"name":"#ESA16 - Nox [Any% Wizard] by Pjoxt","duration":2834,"src":"wa2I7ewDj1U"},{"name":"#ESA16 - Dragon Age: Origins [Any%] by Fatzke","duration":3349,"src":"lqDLM0H97XY"},{"name":"#ESA16 - Super Smash Bros. Melee [All Events] by Fuzzyness","duration":2510,"src":"ze75rcBicCc"},{"name":"#ESA16 - Crash  Bandicoot (Any% ) by mikl","duration":2960,"src":"_RSH4V2JglU"},{"name":"#ESA16 - Kingdom Hearts Birth by Sleep Final Mix HD [Aqua Critical Level 1 Any%] by RebelDragon95","duration":5256,"src":"ONjLpFrYgUA"},{"name":"#ESA16 - Legend of Kay (Any% RLC) by Muffin42","duration":3334,"src":"cBrDQt_jIgE"},{"name":"#ESA16 - Two Worlds [any%] by Shaddex","duration":230,"src":"lcUk0ceP6lc"},{"name":"#ESA16 - Ultima Underworld II: Labyrinth of Worlds [Any%] by pitpo","duration":1896,"src":"1WcwEP8QE2Q"},{"name":"#ESA16 - Limbo [Any% - Normal Route (Race)] by Yajijy and Zet","duration":2692,"src":"OHZ-1u1Bpuw"},{"name":"#ESA16 - F-Zero GX [Story Mode (Very Hard)] by E_Dragon","duration":1449,"src":"KDOVQd11aaQ"},{"name":"#ESA16 - Aliens versus Predator 2 (Easy Alien campaign) by cruxit","duration":1043,"src":"k7-Ub6UTW5s"},{"name":"#ESA16 - Halo 5: Guardians [Legendary (race)] by Distro and A_Royal_Hobo","duration":7105,"src":"DwDorNOWXik"},{"name":"#ESA16 - Winx Club [Any%] by SerSanju","duration":2637,"src":"wr9IHbdHi7k"},{"name":"#ESA16 - Tetris: The Absolute - The Grand Master 2  [Exhibition block] by Qlex","duration":1085,"src":"DRxzb8GV3MI"},{"name":"#ESA16 - Shadow Complex Remastered [NG+ 100% Insane] by Greenalink","duration":3953,"src":"CT1VK9tYyck"},{"name":"#ESA16 - Jade Cocoon: Story of the Tamamayu [Any%] by JackOfHearts","duration":3533,"src":"a8Zht_H_bEg"},{"name":"#ESA16 - Doritos Crash Course (Any% (No Chicken) (Race)) by Respirte and Bensagram","duration":1449,"src":"zHzhpvFc9Ms"},{"name":"#ESA16 - Ooze (Action 52) [Any%] by Alko","duration":452,"src":"8mxJlrZWMFs"},{"name":"#ESA16 - Quake [Any%] by Elgu","duration":1028,"src":"HV0lZkI7V6g"},{"name":"#ESA16 - Kirby Super Star Ultra [100%] by Kinnin11","duration":7754,"src":"LYC5XbwHods"},{"name":"#ESA16 - SOMA (Any%) by Nord","duration":4800,"src":"9ifEDISC8qQ"},{"name":"#ESA16 - Cornerstone [any% speedrun routing race]","duration":2725,"src":"NtgTAUaZj1U"},{"name":"#ESA16 - Donkey Kong '94 [Any%] by Shiekrunner","duration":4398,"src":"QFWwnAPMOt8"},{"name":"#ESA16 - Disney's Tarzan [Any% (easy) race] by china, Joelnir, Jazzy, T1g3r_94","duration":1424,"src":"hOcwRmj2_rQ"},{"name":"#ESA16 - Ninja Gaiden (NES) [2 Players 1 Controller] by InfestedRiche and dxtr","duration":887,"src":"bC38k5smVaY"},{"name":"#ESA16 - Beetle Adventure Racing! [Bonus Circuit, max points] by andypanther","duration":2296,"src":"kGutbPhTj-U"},{"name":"#ESA16 - Tetris The Grand Master [Exhibition block] by Qlex","duration":834,"src":"r26GbLguyU0"},{"name":"#ESA16 - Phantasy Star II [Any%] by kruskader","duration":2667,"src":"m6pdrpIzkHc"},{"name":"#ESA16 - Oddworld: Abe's Oddysee [Any%] by Samtastic","duration":825,"src":"a2fhy_eZR5k"},{"name":"#ESA16 - Axiom Verge [Any% (Race)] by Brother_main and Zecks","duration":2290,"src":"njX8gTwSuao"},{"name":"#ESA16 - Metroid Prime 2: Echoes [Any%] by E_Dragon","duration":5598,"src":"j6QTs7WLDOg"},{"name":"#ESA16 - DuckTales [Any% (Difficult) (Race)] by Nudua, dxtr, Purjo83 and EndySWE","duration":551,"src":"jX9yxJngYlo"},{"name":"#ESA16 - Magical Quest 3 Starring Mickey and Donald [Easy w/ Donald (Solo Run)] by alowishus","duration":1878,"src":"Be4Fgy8Xnwo"},{"name":"#ESA16 - Mega Man 7 [Any%] by Joka","duration":3137,"src":"xWCG_9dHPUY"},{"name":"#ESA16 - Star Fox Zero [Any%] by Pottoww","duration":2060,"src":"EKcZ4rowwtE"},{"name":"#ESA16 - Ori and the Blind Forest Definitive Edition [All Skills, no OOB] by joka","duration":2395,"src":"ceeX21Ymsdw"},{"name":"#ESA16 - Portal [No OOB] by karl__k","duration":892,"src":"3h-9R9pY-Jg"},{"name":"#ESA16 - Metal Gear MSX (Any%) by Pogington","duration":1760,"src":"jfbNJkGOISA"},{"name":"#ESA16 - Batman: The Video Game (NES) [Any% (Race)] by EndySWE, dxtr and infestedriche","duration":681,"src":"7SBIuO4AUss"},{"name":"#ESA16 - Castlevania: Symphony of the Night [Any% No Save Corruption] by Metako","duration":1208,"src":"wnwttCR6KJQ"},{"name":"#ESA16 - Quake II (PC) [Any% (Easy)] by Brainfluid","duration":1436,"src":"l5k654sAhbA"},{"name":"#ESA16 - X-Men: Mojo World [Any% Suicidal (Race)] by FingersTehHand and Robosparkle","duration":844,"src":"3iWqSpzCVwQ"},{"name":"#ESA16 - Pikmin 3 [Any%] by 360Chrism","duration":3673,"src":"OenSl5RqQEI"},{"name":"#ESA16 - inFAMOUS Festival of Blood [Any%] by SerSanju","duration":1590,"src":"TI0V-VHrxZE"},{"name":"#ESA16 - SEGA Bass Fishing [Any%] by Fuzzyness","duration":455,"src":"gXT8_CZ5Q4I"},{"name":"#ESA16 - The Legend of Dark Witch - Episode 2 [Any%] by Crippe","duration":1462,"src":"je_TQrB_kQ4"},{"name":"#ESA16 - Castlevania: Symphony of the Night [Bonus run] by Metako","duration":740,"src":"gvv6_eFhRec"},{"name":"#ESA16 - Judge Dredd: Dredd vs. Death [CO-OP VS. DEATH] by Arctice and DrTChops","duration":1737,"src":"DeoyaLAKARA"},{"name":"#ESA16 - BattleBlock Theater [Any% No Level Skip (Co-Op)] by SeductiveSpatula and HaosEdge","duration":5267,"src":"YOluckgbJXU"},{"name":"#ESA16 - A Story About My Uncle [Any% NoFling] by PenAgain","duration":1995,"src":"-9te2v69haU"},{"name":"#ESA16 - TLOZ: Four Swords [Any% (Co-Op)] by Baffan and Tompa","duration":1575,"src":"5qPcQiyKg0s"},{"name":"#ESA16 - Koumajou Densetsu 2: Stranger Requiem [Hard] by Shadax","duration":1375,"src":"aHVMOFBbwds"},{"name":"#ESA16 - Quint's Revenge [Any%] by snapcase","duration":1392,"src":"xUO-uwnF5kk"},{"name":"#ESA16 - Q.U.B.E. [Any% (Race)] by Fatzke and etholon","duration":1974,"src":"qtRNrw88UKQ"},{"name":"#ESA16 - Mega Man [All Levels] by CartinaCow","duration":1336,"src":"bA13LHFcZeA"},{"name":"#ESA16 - Buck Bumble [Any%] by Rueake","duration":2375,"src":"bWiqr6u69PE"},{"name":"#ESA16 - Tiny Toon Adventures (Any%) by Garadas","duration":828,"src":"z0t6fKRHvS4"},{"name":"#ESA16 - Tiny Toon Adventures 3 (Any%) by Edenal","duration":857,"src":"ZR1NQqP8rXA"},{"name":"#ESA16 - Environmental Station Alpha [Any% (inbounds) (Race)] by Jazzy and puppetmaster","duration":1509,"src":"w4qwPCqzQos"},{"name":"#ESA16 - Pulseman [Any% no skid jump] by Naegleria","duration":2878,"src":"GiuBbP3DC9c"},{"name":"#ESA16 - Master of Darkness [Any%] by btrim","duration":1608,"src":"Z8N38-gCpbc"},{"name":"#ESA16 - Kirby's Dream Land [Beat the game] by Fretzi","duration":887,"src":"2gDNB3QrVEw"},{"name":"#ESA16 - Dynowarz: Destruction of Spondylus [Any%] by laml","duration":1193,"src":"yrSMOsYc5_I"},{"name":"#ESA16 - Chip 'N Dale: Rescue Rangers [Any% (Race)] by EndySWE, KrazyRasmus and Nudua","duration":738,"src":"ZfrmIuaBjZU"},{"name":"#ESA16 - F.D.N.Y. Firefighter [Any% (Race)] by bangerra and oasiz","duration":2209,"src":"9Xzrc2CL3q0"},{"name":"#ESA16 - Wrack (Any%) by PenAgain","duration":1039,"src":"7sZ6cfqoeeA"},{"name":"#ESA16 - Lara Croft and the Guardian of Light [Any% NG+ (Co-Op)] by randompinkbunny, DrTChops and Dr","duration":1636,"src":"VWblR91Iq-4"},{"name":"#ESA16 - The Flash [Any%] by RoboSparkle","duration":1099,"src":"SyyqrJy5GJw"},{"name":"#ESA16 - Chex Quest 3 [UV Any%] by Freddeh","duration":1413,"src":"AGScfWEMKuo"},{"name":"#ESA16 - Mega Turrican [Any%] by Burb","duration":1325,"src":"sRn-cu_8bvw"},{"name":"#ESA16 - The Lucky Dime Caper Starring Donald Duck [Any% (Race)] by KrazyRasmus and btrim","duration":1721,"src":"NfNc98NTsDw"},{"name":"#ESA16 - Chiki Chiki Boys [Any% Blue Twin] by JohnUK89","duration":1241,"src":"jhh9_bWJejI"},{"name":"#ESA16 - The Addams Family [Any%] by IndDragPack","duration":544,"src":"KhESclepc70"},{"name":"#ESA16 - River City Ransom [Any%] by Niss3","duration":608,"src":"hcSKQshxiLU"},{"name":"#ESA16 - The Addams Family (GB) [All Bosses] by bangerra","duration":670,"src":"MqegURz1lYc"},{"name":"#ESA16 - FAST Racing NEO [Time Attack (Race)] by E_Dragon, PreFiXAUT and DivisionX","duration":1942,"src":"DXj_blNoWYE"},{"name":"#ESA16 - Gremlins 2: The New Batch [Any% (Race)] by InfestedRiche and EndySWE","duration":560,"src":"ViuJ00EOe5Y"},{"name":"#ESA16 - DuckTales 2 [Any% (Difficult)] by Garadas","duration":670,"src":"lFH1S08yc4Y"},{"name":"#ESA16 - Legend of Illusion starring Mickey Mouse [Any%] by btrim","duration":964,"src":"IeLnzPgr5GI"},{"name":"#ESA16 - Kero Blaster (Any%) by Shadax","duration":2150,"src":"oZRdPl6XmG8"},{"name":"#ESA16 - Escape Goat 2 [Any%] by Arctice","duration":1246,"src":"3Fw1vj7GI9A"},{"name":"#ESA16 - Yume Penguin Monogatari (Any% (Race)) by CartinaCow and EndySWE","duration":664,"src":"64CM8biOfmg"},{"name":"#ESA16 - Metal Storm [Any% (1loop)] by dxtr","duration":836,"src":"t3cGzwRIMw8"},{"name":"#ESA16 - X-Men: Mojo World [Any% Suicidal (Race)] by FingersTehHand and Robosparkle","duration":844,"src":"3iWqSpzCVwQ"},{"name":"#ESA16 - Pikmin 3 [Any%] by 360Chrism","duration":3673,"src":"OenSl5RqQEI"},{"name":"#ESA16 - inFAMOUS Festival of Blood [Any%] by SerSanju","duration":1590,"src":"TI0V-VHrxZE"},{"name":"#ESA16 - SEGA Bass Fishing [Any%] by Fuzzyness","duration":455,"src":"gXT8_CZ5Q4I"},{"name":"#ESA16 - The Legend of Dark Witch - Episode 2 [Any%] by Crippe","duration":1462,"src":"je_TQrB_kQ4"},{"name":"#ESA16 - Castlevania: Symphony of the Night [Bonus run] by Metako","duration":740,"src":"gvv6_eFhRec"},{"name":"#ESA16 - Judge Dredd: Dredd vs. Death [CO-OP VS. DEATH] by Arctice and DrTChops","duration":1737,"src":"DeoyaLAKARA"},{"name":"#ESA16 - BattleBlock Theater [Any% No Level Skip (Co-Op)] by SeductiveSpatula and HaosEdge","duration":5267,"src":"YOluckgbJXU"},{"name":"#ESA16 - A Story About My Uncle [Any% NoFling] by PenAgain","duration":1995,"src":"-9te2v69haU"},{"name":"#ESA16 - TLOZ: Four Swords [Any% (Co-Op)] by Baffan and Tompa","duration":1575,"src":"5qPcQiyKg0s"},{"name":"#ESA16 - Koumajou Densetsu 2: Stranger Requiem [Hard] by Shadax","duration":1375,"src":"aHVMOFBbwds"},{"name":"#ESA16 - Quint's Revenge [Any%] by snapcase","duration":1392,"src":"xUO-uwnF5kk"},{"name":"#ESA16 - Q.U.B.E. [Any% (Race)] by Fatzke and etholon","duration":1974,"src":"qtRNrw88UKQ"},{"name":"#ESA16 - Mega Man [All Levels] by CartinaCow","duration":1336,"src":"bA13LHFcZeA"},{"name":"#ESA16 - Buck Bumble [Any%] by Rueake","duration":2375,"src":"bWiqr6u69PE"},{"name":"#ESA16 - Tiny Toon Adventures (Any%) by Garadas","duration":828,"src":"z0t6fKRHvS4"},{"name":"#ESA16 - Tiny Toon Adventures 3 (Any%) by Edenal","duration":857,"src":"ZR1NQqP8rXA"},{"name":"#ESA16 - Environmental Station Alpha [Any% (inbounds) (Race)] by Jazzy and puppetmaster","duration":1509,"src":"w4qwPCqzQos"},{"name":"#ESA16 - Pulseman [Any% no skid jump] by Naegleria","duration":2878,"src":"GiuBbP3DC9c"},{"name":"#ESA16 - Master of Darkness [Any%] by btrim","duration":1608,"src":"Z8N38-gCpbc"},{"name":"#ESA16 - Kirby's Dream Land [Beat the game] by Fretzi","duration":887,"src":"2gDNB3QrVEw"},{"name":"#ESA16 - Dynowarz: Destruction of Spondylus [Any%] by laml","duration":1193,"src":"yrSMOsYc5_I"},{"name":"#ESA16 - Chip 'N Dale: Rescue Rangers [Any% (Race)] by EndySWE, KrazyRasmus and Nudua","duration":738,"src":"ZfrmIuaBjZU"},{"name":"#ESA16 - F.D.N.Y. Firefighter [Any% (Race)] by bangerra and oasiz","duration":2209,"src":"9Xzrc2CL3q0"},{"name":"#ESA16 - Wrack (Any%) by PenAgain","duration":1039,"src":"7sZ6cfqoeeA"},{"name":"#ESA16 - Lara Croft and the Guardian of Light [Any% NG+ (Co-Op)] by randompinkbunny, DrTChops and Dr","duration":1636,"src":"VWblR91Iq-4"},{"name":"#ESA16 - The Flash [Any%] by RoboSparkle","duration":1099,"src":"SyyqrJy5GJw"},{"name":"#ESA16 - Chex Quest 3 [UV Any%] by Freddeh","duration":1413,"src":"AGScfWEMKuo"},{"name":"#ESA16 - Mega Turrican [Any%] by Burb","duration":1325,"src":"sRn-cu_8bvw"},{"name":"#ESA16 - The Lucky Dime Caper Starring Donald Duck [Any% (Race)] by KrazyRasmus and btrim","duration":1721,"src":"NfNc98NTsDw"},{"name":"#ESA16 - Chiki Chiki Boys [Any% Blue Twin] by JohnUK89","duration":1241,"src":"jhh9_bWJejI"},{"name":"#ESA16 - The Addams Family [Any%] by IndDragPack","duration":544,"src":"KhESclepc70"},{"name":"#ESA16 - River City Ransom [Any%] by Niss3","duration":608,"src":"hcSKQshxiLU"},{"name":"#ESA16 - The Addams Family (GB) [All Bosses] by bangerra","duration":670,"src":"MqegURz1lYc"},{"name":"#ESA16 - FAST Racing NEO [Time Attack (Race)] by E_Dragon, PreFiXAUT and DivisionX","duration":1942,"src":"DXj_blNoWYE"},{"name":"#ESA16 - Gremlins 2: The New Batch [Any% (Race)] by InfestedRiche and EndySWE","duration":560,"src":"ViuJ00EOe5Y"},{"name":"#ESA16 - DuckTales 2 [Any% (Difficult)] by Garadas","duration":670,"src":"lFH1S08yc4Y"},{"name":"#ESA16 - Legend of Illusion starring Mickey Mouse [Any%] by btrim","duration":964,"src":"IeLnzPgr5GI"},{"name":"#ESA16 - Kero Blaster (Any%) by Shadax","duration":2150,"src":"oZRdPl6XmG8"},{"name":"#ESA16 - Escape Goat 2 [Any%] by Arctice","duration":1246,"src":"3Fw1vj7GI9A"},{"name":"#ESA16 - Yume Penguin Monogatari (Any% (Race)) by CartinaCow and EndySWE","duration":664,"src":"64CM8biOfmg"},{"name":"#ESA16 - Metal Storm [Any% (1loop)] by dxtr","duration":836,"src":"t3cGzwRIMw8"}]}